HelperFunctionsLiam167/__init__.py
HelperFunctionsLiam167/headingCell.py
HelperFunctionsLiam167/kpiFunctions.py
HelperFunctionsLiam167/plotlyFunctions.py
HelperFunctionsLiam167/tableFunctions.py
helperfunctionsliam167-0.1.9.dist-info/METADATA
helperfunctionsliam167-0.1.9.dist-info/WHEEL
helperfunctionsliam167-0.1.9.dist-info/top_level.txt
helperfunctionsliam167-0.1.9.dist-info/RECORD
