Metadata-Version: 2.4
Name: HelperFunctionsLiam167
Version: 0.1.9
Summary: Reusable Plotly/Colab helpers for analytics
Author: Liam Crowley
Requires-Dist: plotly
Requires-Dist: pandas
Dynamic: author
Dynamic: requires-dist
Dynamic: summary
